Metadata-Version: 1.0
Name: iso-distributions
Version: 0.1
Summary: Gaussian distributions
Home-page: UNKNOWN
Author: Samuel Agbanagba
Author-email: agbanagba.samuel@gmail.com
License: UNKNOWN
Platform: UNKNOWN
